{
  "/_app": "pages/_app.js",
  "/_error": "pages/_error.js",
  "/_document": "pages/_document.js",
  "/acesso-negado": "pages/acesso-negado.html",
  "/api/approve-payment": "pages/api/approve-payment.js",
  "/api/integrations": "pages/api/integrations.js",
  "/api/products": "pages/api/products.js",
  "/api/pushinpay": "pages/api/pushinpay.js",
  "/api/send-event": "pages/api/send-event.js",
  "/checkout/[id]": "pages/checkout/[id].html",
  "/checkout/obrigado": "pages/checkout/obrigado.html",
  "/dashboard": "pages/dashboard.html",
  "/forgot-password": "pages/forgot-password.html",
  "/": "pages/index.html",
  "/integracao": "pages/integracao.html",
  "/integracao/pixel": "pages/integracao/pixel.html",
  "/integracao/pushinpay": "pages/integracao/pushinpay.html",
  "/login": "pages/login.html",
  "/perfil": "pages/perfil.html",
  "/produtos": "pages/produtos.html",
  "/register": "pages/register.html",
  "/relatorio": "pages/relatorio.html",
  "/404": "pages/404.html"
}